kucoin/__init__.py
py_kucoin-0.1.0.dist-info/METADATA
py_kucoin-0.1.0.dist-info/WHEEL
py_kucoin-0.1.0.dist-info/top_level.txt
py_kucoin-0.1.0.dist-info/RECORD
